reconcile/__init__.py
reconcile/acs_notifiers.py
reconcile/acs_policies.py
reconcile/acs_rbac.py
reconcile/aws_ami_share.py
reconcile/aws_ecr_image_pull_secrets.py
reconcile/aws_garbage_collector.py
reconcile/aws_iam_keys.py
reconcile/aws_iam_password_reset.py
reconcile/aws_support_cases_sos.py
reconcile/blackbox_exporter_endpoint_monitoring.py
reconcile/checkpoint.py
reconcile/cli.py
reconcile/closedbox_endpoint_monitoring_base.py
reconcile/cluster_deployment_mapper.py
reconcile/dashdotdb_base.py
reconcile/dashdotdb_cso.py
reconcile/dashdotdb_dora.py
reconcile/dashdotdb_dvo.py
reconcile/dashdotdb_slo.py
reconcile/database_access_manager.py
reconcile/deadmanssnitch.py
reconcile/email_sender.py
reconcile/gabi_authorized_users.py
reconcile/gcr_mirror.py
reconcile/github_org.py
reconcile/github_owners.py
reconcile/github_repo_invites.py
reconcile/github_repo_permissions_validator.py
reconcile/github_users.py
reconcile/github_validator.py
reconcile/gitlab_fork_compliance.py
reconcile/gitlab_housekeeping.py
reconcile/gitlab_labeler.py
reconcile/gitlab_members.py
reconcile/gitlab_mr_sqs_consumer.py
reconcile/gitlab_owners.py
reconcile/gitlab_permissions.py
reconcile/gitlab_projects.py
reconcile/integrations_manager.py
reconcile/jenkins_base.py
reconcile/jenkins_job_builder.py
reconcile/jenkins_job_builds_cleaner.py
reconcile/jenkins_job_cleaner.py
reconcile/jenkins_roles.py
reconcile/jenkins_webhooks.py
reconcile/jenkins_webhooks_cleaner.py
reconcile/jenkins_worker_fleets.py
reconcile/jira_permissions_validator.py
reconcile/jira_watcher.py
reconcile/ldap_users.py
reconcile/mr_client_gateway.py
reconcile/ocm_additional_routers.py
reconcile/ocm_addons.py
reconcile/ocm_addons_upgrade_tests_trigger.py
reconcile/ocm_aws_infrastructure_access.py
reconcile/ocm_clusters.py
reconcile/ocm_external_configuration_labels.py
reconcile/ocm_github_idp.py
reconcile/ocm_groups.py
reconcile/ocm_machine_pools.py
reconcile/ocm_update_recommended_version.py
qontract_reconcile-0.10.1.dist-info/METADATA
qontract_reconcile-0.10.1.dist-info/WHEEL
qontract_reconcile-0.10.1.dist-info/entry_points.txt
qontract_reconcile-0.10.1.dist-info/RECORD
