Metadata-Version: 2.3
Name: qontract-reconcile
Version: 0.10.1
Summary: Collection of tools to reconcile services with their desired state as defined in the app-interface DB.
Project-URL: homepage, https://github.com/app-sre/qontract-reconcile
Project-URL: repository, https://github.com/app-sre/qontract-reconcile
Project-URL: documentation, https://github.com/app-sre/qontract-reconcile
Author-email: Red Hat App-SRE Team <sd-app-sre@redhat.com>
License: Apache 2.0
Classifier: Development Status :: 2 - Pre-Alpha
Classifier: Programming Language :: Python
Classifier: Programming Language :: Python :: 3
Classifier: Programming Language :: Python :: 3.11
Classifier: Programming Language :: Python :: 3.12
Classifier: Programming Language :: Python :: 3.13
Requires-Python: >=3.11
Requires-Dist: anymarkup<0.9.0,>=0.7.0
Requires-Dist: boto3==1.34.94
Requires-Dist: botocore==1.34.94
Requires-Dist: click<9.0,>=7.0
Requires-Dist: croniter<1.1.0,>=1.0.15
Requires-Dist: dateparser~=1.1.7
Requires-Dist: deepdiff==6.7.1
Requires-Dist: dnspython~=2.1
Requires-Dist: dt==1.1.61
Requires-Dist: filetype~=1.2.0
Requires-Dist: gql==3.1.0
Requires-Dist: hvac<0.8.0,>=0.7.0
Requires-Dist: jenkins-job-builder~=4.3.0
Requires-Dist: jinja2<3.2.0,>=2.10.1
Requires-Dist: jira~=3.1
Requires-Dist: jsonpatch~=1.33
Requires-Dist: jsonpath-ng==1.5.3
Requires-Dist: jsonpath-rw<1.5.0,>=1.4.0
Requires-Dist: jsonpointer~=2.4
Requires-Dist: kubernetes~=24.0
Requires-Dist: ldap3<2.10.0,>=2.9.1
Requires-Dist: markupsafe==2.1.1
Requires-Dist: networkx~=2.8
Requires-Dist: parse==1.18.0
Requires-Dist: prometheus-client~=0.8
Requires-Dist: psycopg2-binary~=2.9
Requires-Dist: pydantic~=1.10.6
Requires-Dist: pygithub<1.59,>=1.58
Requires-Dist: pyjwt~=2.7
Requires-Dist: pyopenssl~=23.0
Requires-Dist: pypd<1.2.0,>=1.1.0
Requires-Dist: python-gitlab~=4.6
Requires-Dist: requests-oauthlib~=1.3
Requires-Dist: requests~=2.32
Requires-Dist: rich<14.0.0,>=13.3.0
Requires-Dist: ruamel-yaml<0.18.0,>=0.17.22
Requires-Dist: semver~=3.0
Requires-Dist: sendgrid<6.5.0,>=6.4.8
Requires-Dist: sentry-sdk~=2.0
Requires-Dist: slack-sdk<4.0,>=3.10
Requires-Dist: sretoolbox~=2.6
Requires-Dist: sshtunnel>=0.4.0
Requires-Dist: tabulate<0.9.0,>=0.8.6
Requires-Dist: terrascript==0.9.0
Requires-Dist: toml<0.11.0,>=0.10.0
Requires-Dist: unleashclient~=5.11
Requires-Dist: urllib3~=2.2
Requires-Dist: websocket-client<0.55.0,>=0.35
Requires-Dist: yamllint==1.34.0
